discord_notify/__init__.py
discord_notify-1.0.0.dist-info/LICENSE
discord_notify-1.0.0.dist-info/METADATA
discord_notify-1.0.0.dist-info/WHEEL
discord_notify-1.0.0.dist-info/top_level.txt
discord_notify-1.0.0.dist-info/RECORD
