Metadata-Version: 2.1
Name: discord_notify
Version: 1.0.0
Summary: A minimal Discord API webhooks wrapper for sending messages to a Discord channel
Home-page: https://github.com/MatthewATaylor/discord_notify
Author: Matthew Taylor
Author-email: matthewalantaylor2@gmail.com
License: MIT
Keywords: discord webhooks logging
Platform: UNKNOWN
Classifier: Development Status :: 3 - Alpha
Classifier: Intended Audience :: Developers
Classifier: License :: OSI Approved :: MIT License
Classifier: Programming Language :: Python :: 3 :: Only
Classifier: Topic :: System :: Logging
Classifier: Topic :: Communications :: Chat
Classifier: Topic :: Utilities
